textxtract/__init__.py
textxtract/exceptions.py
textxtract/aio/__init__.py
textxtract/aio/extractor.py
textxtract/core/__init__.py
textxtract/core/base.py
textxtract/core/config.py
textxtract/core/exceptions.py
textxtract/core/logging_config.py
textxtract/core/registry.py
textxtract/core/utils.py
textxtract/handlers/__init__.py
textxtract/handlers/csv.py
textxtract/handlers/doc.py
textxtract/handlers/docx.py
textxtract/handlers/html.py
textxtract/handlers/json.py
textxtract/handlers/md.py
textxtract/handlers/pdf.py
textxtract/handlers/rtf.py
textxtract/handlers/txt.py
textxtract/handlers/xml.py
textxtract/handlers/zip.py
textxtract/sync/__init__.py
textxtract/sync/extractor.py
textxtract-0.2.2.dist-info/licenses/LICENSE
textxtract-0.2.2.dist-info/METADATA
textxtract-0.2.2.dist-info/WHEEL
textxtract-0.2.2.dist-info/top_level.txt
textxtract-0.2.2.dist-info/RECORD
