Metadata-Version: 2.4
Name: textxtract
Version: 0.2.2
Summary: A robust, extensible Python package for synchronous and asynchronous text extraction from PDF, DOCX, DOC, TXT, ZIP, MD, RTF, HTML, and more.
Author-email: 10xScale <contact@hire10x.ai>, Shudipto Trafder <shudipto.trafder@hire10x.ai>
Project-URL: Homepage, https://10xscale-in.github.io/textxtract/
Project-URL: Documentation, https://10xscale-in.github.io/textxtract/
Project-URL: Source, https://github.com/10XScale-in/textxtract
Requires-Python: >=3.9
License-File: LICENSE
Provides-Extra: pdf
Requires-Dist: pymupdf; extra == "pdf"
Provides-Extra: docx
Requires-Dist: python-docx; extra == "docx"
Provides-Extra: doc
Requires-Dist: antiword; extra == "doc"
Provides-Extra: md
Requires-Dist: markdown; extra == "md"
Provides-Extra: rtf
Requires-Dist: pyrtf-ng; extra == "rtf"
Provides-Extra: html
Requires-Dist: beautifulsoup4; extra == "html"
Requires-Dist: lxml; extra == "html"
Provides-Extra: xml
Requires-Dist: lxml; extra == "xml"
Provides-Extra: all
Requires-Dist: pymupdf; extra == "all"
Requires-Dist: python-docx; extra == "all"
Requires-Dist: antiword; extra == "all"
Requires-Dist: markdown; extra == "all"
Requires-Dist: pyrtf-ng; extra == "all"
Requires-Dist: beautifulsoup4; extra == "all"
Requires-Dist: lxml; extra == "all"
Provides-Extra: dev
Requires-Dist: pytest>=7.0; extra == "dev"
Requires-Dist: pytest-asyncio; extra == "dev"
Requires-Dist: mkdocs; extra == "dev"
Requires-Dist: mkdocs-material; extra == "dev"
Requires-Dist: mkdocstrings[python]; extra == "dev"
Requires-Dist: pytest-cov; extra == "dev"
Dynamic: license-file
